<?xml version="1.0" encoding="utf-8" ?>
<dwsync>
<file name="homepage_1.jpg" server="zestwebdemos.net/zestwebdemos.net/htdocs/iw/" local="129683546111107538" remote="129685234800000000" />
<file name="homepage_2.jpg" server="zestwebdemos.net/zestwebdemos.net/htdocs/iw/" local="129683546216653574" remote="129685234800000000" />
<file name="kefalonia_1.jpg" server="zestwebdemos.net/zestwebdemos.net/htdocs/iw/" local="129685263006401127" remote="129685267200000000" />
<file name="kefalonia_2.jpg" server="zestwebdemos.net/zestwebdemos.net/htdocs/iw/" local="129685262805509637" remote="129685267200000000" />
<file name="kefalonia_3.jpg" server="zestwebdemos.net/zestwebdemos.net/htdocs/iw/" local="129685263501099422" remote="129685267200000000" />
<file name="kefalonia_4.jpg" server="zestwebdemos.net/zestwebdemos.net/htdocs/iw/" local="129685262608708380" remote="129685267200000000" />
<file name="kefalonia_5.jpg" server="zestwebdemos.net/zestwebdemos.net/htdocs/iw/" local="129685263806836909" remote="129685267200000000" />
<file name="kos_1.jpg" server="zestwebdemos.net/zestwebdemos.net/htdocs/iw/" local="129685263391703165" remote="129685267200000000" />
<file name="kos_2.jpg" server="zestwebdemos.net/zestwebdemos.net/htdocs/iw/" local="129685264478495326" remote="129685267200000000" />
<file name="kos_3.jpg" server="zestwebdemos.net/zestwebdemos.net/htdocs/iw/" local="129685262356283942" remote="129685267200000000" />
<file name="kos_4.jpg" server="zestwebdemos.net/zestwebdemos.net/htdocs/iw/" local="129685262880913950" remote="129685267200000000" />
<file name="kos_5.jpg" server="zestwebdemos.net/zestwebdemos.net/htdocs/iw/" local="129685263715281673" remote="129685267200000000" />
<file name="rhodes_1.jpg" server="zestwebdemos.net/zestwebdemos.net/htdocs/iw/" local="129685264506676938" remote="129685267200000000" />
<file name="rhodes_10.jpg" server="zestwebdemos.net/zestwebdemos.net/htdocs/iw/" local="129685262727735188" remote="129685267200000000" />
<file name="rhodes_11.jpg" server="zestwebdemos.net/zestwebdemos.net/htdocs/iw/" local="129685264144316212" remote="129685267200000000" />
<file name="rhodes_12.jpg" server="zestwebdemos.net/zestwebdemos.net/htdocs/iw/" local="129685264193669035" remote="129685267200000000" />
<file name="rhodes_13.jpg" server="zestwebdemos.net/zestwebdemos.net/htdocs/iw/" local="129685263134258440" remote="129685267200000000" />
<file name="rhodes_14.jpg" server="zestwebdemos.net/zestwebdemos.net/htdocs/iw/" local="129685263076465134" remote="129685267200000000" />
<file name="rhodes_15.jpg" server="zestwebdemos.net/zestwebdemos.net/htdocs/iw/" local="129685263614885930" remote="129685267200000000" />
<file name="rhodes_2.jpg" server="zestwebdemos.net/zestwebdemos.net/htdocs/iw/" local="129685262956508273" remote="129685267200000000" />
<file name="rhodes_3.jpg" server="zestwebdemos.net/zestwebdemos.net/htdocs/iw/" local="129685264546289204" remote="129685267200000000" />
<file name="rhodes_4.jpg" server="zestwebdemos.net/zestwebdemos.net/htdocs/iw/" local="129685262527083712" remote="129685267200000000" />
<file name="rhodes_5.jpg" server="zestwebdemos.net/zestwebdemos.net/htdocs/iw/" local="129685263349330741" remote="129685267200000000" />
<file name="rhodes_6.jpg" server="zestwebdemos.net/zestwebdemos.net/htdocs/iw/" local="129685262689963028" remote="129685267200000000" />
<file name="rhodes_7.jpg" server="zestwebdemos.net/zestwebdemos.net/htdocs/iw/" local="129685264402710991" remote="129685267200000000" />
<file name="rhodes_8.jpg" server="zestwebdemos.net/zestwebdemos.net/htdocs/iw/" local="129685262399576419" remote="129685267200000000" />
<file name="rhodes_9.jpg" server="zestwebdemos.net/zestwebdemos.net/htdocs/iw/" local="129685262496261949" remote="129685267200000000" />
<file name="santorini_1.jpg" server="zestwebdemos.net/zestwebdemos.net/htdocs/iw/" local="129685263190821675" remote="129685267200000000" />
<file name="santorini_10.jpg" server="zestwebdemos.net/zestwebdemos.net/htdocs/iw/" local="129685264253222441" remote="129685267200000000" />
<file name="santorini_11.jpg" server="zestwebdemos.net/zestwebdemos.net/htdocs/iw/" local="129685263306788308" remote="129685267200000000" />
<file name="santorini_12.jpg" server="zestwebdemos.net/zestwebdemos.net/htdocs/iw/" local="129685262919236141" remote="129685267200000000" />
<file name="santorini_13.jpg" server="zestwebdemos.net/zestwebdemos.net/htdocs/iw/" local="129685263983467012" remote="129685267200000000" />
<file name="santorini_14.jpg" server="zestwebdemos.net/zestwebdemos.net/htdocs/iw/" local="129685264353818195" remote="129685267200000000" />
<file name="santorini_15.jpg" server="zestwebdemos.net/zestwebdemos.net/htdocs/iw/" local="129685264308925627" remote="129685267200000000" />
<file name="santorini_16.jpg" server="zestwebdemos.net/zestwebdemos.net/htdocs/iw/" local="129685263666158863" remote="129685267200000000" />
<file name="santorini_17.jpg" server="zestwebdemos.net/zestwebdemos.net/htdocs/iw/" local="129685264054221059" remote="129685267200000000" />
<file name="santorini_18.jpg" server="zestwebdemos.net/zestwebdemos.net/htdocs/iw/" local="129685263255525376" remote="129685267200000000" />
<file name="santorini_19.jpg" server="zestwebdemos.net/zestwebdemos.net/htdocs/iw/" local="129685262771957718" remote="129685267200000000" />
<file name="santorini_2.jpg" server="zestwebdemos.net/zestwebdemos.net/htdocs/iw/" local="129685261114282904" remote="129685267200000000" />
<file name="santorini_20.jpg" server="zestwebdemos.net/zestwebdemos.net/htdocs/iw/" local="129685261154335195" remote="129685267200000000" />
<file name="santorini_21.jpg" server="zestwebdemos.net/zestwebdemos.net/htdocs/iw/" local="129685261041958767" remote="129685267200000000" />
<file name="santorini_3.jpg" server="zestwebdemos.net/zestwebdemos.net/htdocs/iw/" local="129685260999056313" remote="129685267200000000" />
<file name="santorini_4.jpg" server="zestwebdemos.net/zestwebdemos.net/htdocs/iw/" local="129685260793164537" remote="129685267200000000" />
<file name="santorini_5.jpg" server="zestwebdemos.net/zestwebdemos.net/htdocs/iw/" local="129685260952003622" remote="129685267200000000" />
<file name="santorini_6.jpg" server="zestwebdemos.net/zestwebdemos.net/htdocs/iw/" local="129685260907881099" remote="129685267200000000" />
<file name="santorini_7.jpg" server="zestwebdemos.net/zestwebdemos.net/htdocs/iw/" local="129685260697819084" remote="129685267200000000" />
<file name="santorini_8.jpg" server="zestwebdemos.net/zestwebdemos.net/htdocs/iw/" local="129685260659336883" remote="129685267200000000" />
<file name="santorini_9.jpg" server="zestwebdemos.net/zestwebdemos.net/htdocs/iw/" local="129685260740291513" remote="129685267200000000" />
<file name="zante_1.jpg" server="zestwebdemos.net/zestwebdemos.net/htdocs/iw/" local="129685260563221385" remote="129685267200000000" />
<file name="zante_10.jpg" server="zestwebdemos.net/zestwebdemos.net/htdocs/iw/" local="129685260611264133" remote="129685267200000000" />
<file name="zante_2.jpg" server="zestwebdemos.net/zestwebdemos.net/htdocs/iw/" local="129685260490417221" remote="129685267200000000" />
<file name="zante_3.jpg" server="zestwebdemos.net/zestwebdemos.net/htdocs/iw/" local="129685260384001134" remote="129685267200000000" />
<file name="zante_4.jpg" server="zestwebdemos.net/zestwebdemos.net/htdocs/iw/" local="129685260321327550" remote="129685267200000000" />
<file name="zante_5.jpg" server="zestwebdemos.net/zestwebdemos.net/htdocs/iw/" local="129685260120716075" remote="129685267200000000" />
<file name="zante_6.jpg" server="zestwebdemos.net/zestwebdemos.net/htdocs/iw/" local="129685260271984727" remote="129685267200000000" />
<file name="zante_7.jpg" server="zestwebdemos.net/zestwebdemos.net/htdocs/iw/" local="129685260225822087" remote="129685267200000000" />
<file name="zante_8.jpg" server="zestwebdemos.net/zestwebdemos.net/htdocs/iw/" local="129685260173069070" remote="129685267200000000" />
<file name="zante_9.jpg" server="zestwebdemos.net/zestwebdemos.net/htdocs/iw/" local="129685260053732244" remote="129685267200000000" />
</dwsync>