<?xml version="1.0" encoding="utf-8"?>
<tn2>
	<gallery>
		<title>Fixed Dimensions</title>
		<description>Some Description</description>
		<file_root>/images/gallery/</file_root>
		<images>
<image>
				<image_src>/117-thalassines1.jpg</image_src>
				<thumb_src>/thumbnail/117-thalassines1.jpg</thumb_src>
			</image>
<image>
				<image_src>/117-thalassines.jpg</image_src>
				<thumb_src>/thumbnail/117-thalassines.jpg</thumb_src>
			</image>
<image>
				<image_src>/117-thalassines5.jpg</image_src>
				<thumb_src>/thumbnail/117-thalassines5.jpg</thumb_src>
			</image>
<image>
				<image_src>/117-thalassines6.jpg</image_src>
				<thumb_src>/thumbnail/117-thalassines6.jpg</thumb_src>
			</image>
<image>
				<image_src>/117-thalassines3.jpg</image_src>
				<thumb_src>/thumbnail/117-thalassines3.jpg</thumb_src>
			</image>
<image>
				<image_src>/117-thalassines4.jpg</image_src>
				<thumb_src>/thumbnail/117-thalassines4.jpg</thumb_src>
			</image>
</images>
	</gallery>
</tn2>

